{
	"select_CallComponentBool": false,
	"textArea_CallComponentBool": false,
	"input_CallComponentBool": true,
	"flatPickr_CallComponentBool": false,
	"checkBox_CallComponentBool": false,
	"nameComponente": "Carrito",
	"divClassNameCol": "col-input col-lg-4 col-md-4 col-sm-4",
	"divIdGrupo": "grupo__cantidad",
	"label_CallComponentBool": false,
	"divClassNameFormularioGrupoInput": "d-flex flex-row formulario__grupo-input",
	"valorInicial": "1",
	"inputId": "cantidad",
	"inputType": "text",
	"inputClassName": "formulario__input-cantidad",
	"nameInput": "cantidad",
	"inputDisabled": true,
	"inputPlaceHolder": "CANTIDAD",
	"pFormularioInputError1Texto": "EL CAMPO CANTIDAD ES OBLIGATORIO.",
	"pFormularioInputErrorTexto": "EL CAMPO CANTIDAD SOLO PUEDE CONTENER NUMEROS, DEBE SER MAYOR QUE 0.",
	"iClassName": "d-flex align-items-center formulario__validacion-estado",
	"fontAwesomeIcon_CallComponentBool": true,
	"fontAwesomeIcon_className": "fas"
}
