[
	{
		"select_CallComponentBool": false,
		"textArea_CallComponentBool": false,
		"input_CallComponentBool": true,
		"flatPickr_CallComponentBool": false,
		"checkBox_CallComponentBool": false,
		"divClassNameCol": "col-lg-12 col-md-12 d-flex justify-content-center",
		"divIdGrupo": "grupo__nombres",
		"label_CallComponentBool": true,
		"labelHtmlFor": "nombres",
		"labelClassName": "formulario__label",
		"labelText": "NOMBRES",
		"divClassNameFormularioGrupoInput": "d-flex flex-row formulario__grupo-input",
		"valorInicial": "",
		"inputId": "nombres",
		"inputType": "text",
		"inputClassName": "formulario__input",
		"nameInput": "nombres",
		"inputDisabled": false,
		"inputPlaceHolder": "INGRESE LOS NOMBRES",
		"pFormularioInputError1Texto": "EL CAMPO NOMBRES ES OBLIGATORIO.",
		"pFormularioInputErrorTexto": "EL CAMPO NOMBRES SOLO PUEDE CONTENER LETRAS Y TIENE UN MINIMO DE 10 Y UN MAXIMO DE 35 CARACTERES.,",
		"iClassName": "d-flex align-items-center formulario__validacion-estado",
		"fontAwesomeIcon_CallComponentBool": true,
		"fontAwesomeIcon_className": "fas"
	},
	{
		"select_CallComponentBool": false,
		"textArea_CallComponentBool": false,
		"input_CallComponentBool": true,
		"flatPickr_CallComponentBool": false,
		"checkBox_CallComponentBool": false,
		"divClassNameCol": "col-lg-12 col-md-12 d-flex justify-content-center",
		"divIdGrupo": "grupo__apellidos",
		"label_CallComponentBool": true,
		"labelHtmlFor": "apellidos",
		"labelClassName": "formulario__label",
		"labelText": "APELLIDOS",
		"divClassNameFormularioGrupoInput": "d-flex flex-row formulario__grupo-input",
		"valorInicial": "",
		"inputId": "apellidos",
		"inputType": "text",
		"inputClassName": "formulario__input",
		"nameInput": "apellidos",
		"inputDisabled": false,
		"inputPlaceHolder": "INGRESE LOS APELLIDOS",
		"pFormularioInputError1Texto": "EL CAMPO APELLIDOS ES OBLIGATORIO.",
		"pFormularioInputErrorTexto": "EL CAMPO APELLIDOS SOLO PUEDE CONTENER LETRAS Y TIENE UN MINIMO DE 10 Y UN MAXIMO DE 35 CARACTERES.,",
		"iClassName": "d-flex align-items-center formulario__validacion-estado",
		"fontAwesomeIcon_CallComponentBool": true,
		"fontAwesomeIcon_className": "fas"
	},
	{
		"select_CallComponentBool": false,
		"textArea_CallComponentBool": false,
		"input_CallComponentBool": true,
		"flatPickr_CallComponentBool": false,
		"checkBox_CallComponentBool": false,
		"divClassNameCol": "col-lg-12 col-md-12 d-flex justify-content-center",
		"divIdGrupo": "grupo__cedula",
		"label_CallComponentBool": true,
		"labelHtmlFor": "cedula",
		"labelClassName": "formulario__label",
		"labelText": "CEDULA",
		"divClassNameFormularioGrupoInput": "d-flex flex-row formulario__grupo-input",
		"valorInicial": "",
		"inputId": "cedula",
		"inputType": "text",
		"inputClassName": "formulario__input",
		"nameInput": "cedula",
		"inputDisabled": false,
		"inputPlaceHolder": "INGRESE LA CEDULA",
		"pFormularioInputError1Texto": "EL CAMPO CEDULA ES OBLIGATORIO.",
		"pFormularioInputErrorTexto": "EL CAMPO CEDULA SOLO PUEDE CONTENER NUMEROS Y UN MAXIMO DE 10 CARACTERES.",
		"iClassName": "d-flex align-items-center formulario__validacion-estado",
		"fontAwesomeIcon_CallComponentBool": true,
		"fontAwesomeIcon_className": "fas"
	},
	{
		"select_CallComponentBool": false,
		"textArea_CallComponentBool": false,
		"input_CallComponentBool": true,
		"flatPickr_CallComponentBool": false,
		"checkBox_CallComponentBool": false,
		"divClassNameCol": "col-lg-12 col-md-12 d-flex justify-content-center",
		"divIdGrupo": "grupo__correo",
		"label_CallComponentBool": true,
		"labelHtmlFor": "correo",
		"labelClassName": "formulario__label",
		"labelText": "CORREO ELECTRONICO",
		"divClassNameFormularioGrupoInput": "d-flex flex-row formulario__grupo-input",
		"valorInicial": "",
		"inputId": "correo",
		"inputType": "email",
		"inputClassName": "formulario__input",
		"nameInput": "correo",
		"inputDisabled": false,
		"inputPlaceHolder": "CORREO@CORREO.COM",
		"pFormularioInputError1Texto": "EL CAMPO CORREO ELECTRONICO ES OBLIGATORIO.",
		"pFormularioInputErrorTexto": "EL CAMPO CORREO ELECTRONICO SOLO PUEDE CONTENER LETRAS, NUMEROS, PUNTOS, GUIONES, ARROVA, GUION BAJO Y MAXIMO DE CARACTERES ES 20.",
		"iClassName": "d-flex align-items-center formulario__validacion-estado",
		"fontAwesomeIcon_CallComponentBool": true,
		"fontAwesomeIcon_className": "fas"
	},
	{
		"select_CallComponentBool": false,
		"textArea_CallComponentBool": false,
		"input_CallComponentBool": true,
		"flatPickr_CallComponentBool": false,
		"checkBox_CallComponentBool": false,
		"divClassNameCol": "col-lg-12 col-md-12 d-flex justify-content-center",
		"divIdGrupo": "grupo__telefono",
		"label_CallComponentBool": true,
		"labelHtmlFor": "telefono",
		"labelClassName": "formulario__label",
		"labelText": "TELEFONO",
		"divClassNameFormularioGrupoInput": "d-flex flex-row formulario__grupo-input",
		"valorInicial": "",
		"inputId": "telefono",
		"inputType": "text",
		"inputClassName": "formulario__input",
		"nameInput": "telefono",
		"inputDisabled": false,
		"inputPlaceHolder": "INGRESE EL TELEFONO",
		"pFormularioInputError1Texto": "EL CAMPO TELEFONO ES OBLIGATORIO.",
		"pFormularioInputErrorTexto": "EL CAMPO TELEFONO SOLO PUEDE CONTENER NUMEROS Y UN MAXIMO DE 10 CARACTERES.",
		"iClassName": "d-flex align-items-center formulario__validacion-estado",
		"fontAwesomeIcon_CallComponentBool": true,
		"fontAwesomeIcon_className": "fas"
	},
	{
		"input_CallComponentBool": false,
		"textArea_CallComponentBool": false,
		"select_CallComponentBool": true,
		"flatPickr_CallComponentBool": false,
		"checkBox_CallComponentBool": false,
		"divClassNameCol": "col-lg-12 col-md-12 d-flex justify-content-center",
		"divIdGrupo": "grupo__servicio",
		"label_CallComponentBool": true,
		"labelHtmlFor": "servicio",
		"labelClassName": "d-flex flex-row align-self-center formulario__label",
		"labelText": "SELECCIONE EL SERVICIO",
		"divClassNameFormularioGrupoInput": "d-flex flex-row formulario__grupo-input align-self-center formulario__grupo-select",
		"valorInicial": "",
		"selectId": "servicio",
		"selectClassName": "d-flex flex-row formulario__input",
		"nameSelect": "servicio",
		"opcionesSelect": [
			{ "value": "CELEBRACIÓN DE CUMPLEAÑOS" },
			{ "value": "ANIVERSARIOS" },
			{ "value": "FIESTAS INFANTILES" },
			{ "value": "DECLARACIONES O PROPUESTAS" },
			{ "value": "DESPEDIDAS" }
		],
		"pFormularioInputError1Texto": "EL CAMPO SERVICIO ES OBLIGATORIO, SELECCIONA UN TIPO DE SERVICIO.",
		"iClassName": "d-flex align-items-center formulario__validacion-estado",
		"fontAwesomeIcon_CallComponentBool": true,
		"fontAwesomeIcon_className": "fas"
	},
	{
		"select_CallComponentBool": false,
		"textArea_CallComponentBool": false,
		"input_CallComponentBool": true,
		"flatPickr_CallComponentBool": false,
		"checkBox_CallComponentBool": false,
		"divClassNameCol": "col-lg-12 col-md-12 d-flex justify-content-center",
		"divIdGrupo": "grupo__cantidadPersonas",
		"label_CallComponentBool": true,
		"labelHtmlFor": "cantidadPersonas",
		"labelClassName": "formulario__label",
		"labelText": "CANTIDAD DE PERSONAS",
		"divClassNameFormularioGrupoInput": "d-flex flex-row formulario__grupo-input",
		"valorInicial": "",
		"inputId": "cantidadPersonas",
		"inputType": "text",
		"inputClassName": "formulario__input",
		"nameInput": "cantidadPersonas",
		"inputDisabled": false,
		"inputPlaceHolder": "INGRESE LA CANTIDAD DE PERSONAS",
		"pFormularioInputError1Texto": "EL CAMPO CANTIDAD DE PERSONAS ES OBLIGATORIO.",
		"pFormularioInputErrorTexto": "EL CAMPO CANTIDAD DE PERSONAS SOLO PUEDE CONTENER NUMEROS.",
		"iClassName": "d-flex align-items-center formulario__validacion-estado",
		"fontAwesomeIcon_CallComponentBool": true,
		"fontAwesomeIcon_className": "fas"
	},
	{
		"select_CallComponentBool": false,
		"textArea_CallComponentBool": false,
		"input_CallComponentBool": false,
		"flatPickr_CallComponentBool": true,
		"checkBox_CallComponentBool": true,
		"divClassNameCol": "col-lg-12 col-md-12 d-flex justify-content-center",
		"divIdGrupo": "grupo__fecha",
		"label_CallComponentBool": true,
		"labelHtmlFor": "fecha",
		"labelClassName": "formulario__label",
		"labelText": "FECHA DE LA RESERVA",
		"divClassNameFormularioGrupoInput": "d-flex flex-row formulario__grupo-input",
		"valorInicial": "",
		"flatPickrId": "fecha",
		"flatPickrOptions": "config_fecha",
		"flatPickrClassName": "formulario__input",
		"nameFlatPickr": "fecha",
		"flatPickrPlaceHolder": "SELECCIONE LA FECHA",
		"pFormularioInputError1Texto": "EL CAMPO FECHA ES OBLIGATORIO.",
		"iClassName": "d-flex align-items-center formulario__validacion-estado",
		"fontAwesomeIcon_CallComponentBool": true,
		"fontAwesomeIcon_className": "fas"
	},
	{
		"select_CallComponentBool": false,
		"textArea_CallComponentBool": false,
		"input_CallComponentBool": false,
		"flatPickr_CallComponentBool": true,
		"checkBox_CallComponentBool": false,
		"divClassNameCol": "col-lg-12 col-md-12 d-flex justify-content-center",
		"divIdGrupo": "grupo__hora",
		"label_CallComponentBool": true,
		"labelHtmlFor": "hora",
		"labelClassName": "formulario__label",
		"labelText": "HORA DE LA RESERVA",
		"divClassNameFormularioGrupoInput": "d-flex flex-row formulario__grupo-input",
		"valorInicial": "",
		"flatPickrId": "hora",
		"flatPickrOptions": "config_hora",
		"flatPickrClassName": "formulario__input",
		"nameFlatPickr": "hora",
		"flatPickrPlaceHolder": "SELECCIONE LA HORA DE LA RESERVA",
		"pFormularioInputError1Texto": "EL CAMPO HORA DE LA RESERVA ES OBLIGATORIO.",
		"iClassName": "d-flex align-items-center formulario__validacion-estado",
		"fontAwesomeIcon_CallComponentBool": true,
		"fontAwesomeIcon_className": "fas"
	},
	{
		"select_CallComponentBool": false,
		"textArea_CallComponentBool": true,
		"input_CallComponentBool": false,
		"flatPickr_CallComponentBool": false,
		"checkBox_CallComponentBool": false,
		"divClassNameCol": "col-lg-12 col-md-12 d-flex justify-content-center",
		"divIdGrupo": "grupo__indicacionesEspeciales",
		"label_CallComponentBool": true,
		"labelHtmlFor": "indicacionesEspeciales",
		"labelClassName": "formulario__label",
		"labelText": "INDICACIONES ESPECIALES",
		"divClassNameFormularioGrupoInput": "d-flex flex-row formulario__grupo-input formulario__grupo-textarea",
		"valorInicial": "",
		"textAreaId": "indicacionesEspeciales",
		"textAreaClassName": "formulario__textarea",
		"nameTextArea": "indicacionesEspeciales",
		"textAreaPlaceHolder": "INGRESE LAS INDICACIONES ESPECIALES",
		"textAreaRow": 5,
		"pFormularioInputError1Texto": "EL CAMPO INDICACIONES ESPECIALES ES OBLIGATORIO.",
		"pFormularioInputErrorTexto": "EL CAMPO INDICACIONES ESPECIALES SOLO PUEDE CONTENER LETRAS, EL MINIMO ES DE 10 Y MAXIMO SON 200 CARACTERES.",
		"iClassName": "d-flex align-items-center formulario__validacion-estado",
		"fontAwesomeIcon_CallComponentBool": true,
		"fontAwesomeIcon_className": "fas"
	},
	{
		"select_CallComponentBool": false,
		"textArea_CallComponentBool": false,
		"input_CallComponentBool": false,
		"flatPickr_CallComponentBool": false,
		"checkBox_CallComponentBool": true,
		"divClassNameCol": "col-lg-12 col-md-12 d-flex justify-content-center",
		"divIdGrupo": "grupo__terminos",
		"label_CallComponentBool": true,
		"labelHtmlFor": "terminos",
		"labelClassName": "formulario__label",
		"labelText": "ACEPTO LOS TERMINOS Y CONDICIONES",
		"valorInicial": false,
		"checkBoxId": "terminos",
		"checkBoxType": "checkbox",
		"checkBoxClassName": "formulario__checkbox",
		"nameCheckBox": "terminos"
	}
]
